MANIFEST.in
README.md
requirements.txt
setup.py
pyguppyclient/__init__.py
pyguppyclient/caller.py
pyguppyclient/client.py
pyguppyclient/decode.py
pyguppyclient/io.py
pyguppyclient/ipc.py
pyguppyclient/utils.py
pyguppyclient.egg-info/PKG-INFO
pyguppyclient.egg-info/SOURCES.txt
pyguppyclient.egg-info/dependency_links.txt
pyguppyclient.egg-info/requires.txt
pyguppyclient.egg-info/top_level.txt
pyguppyclient/guppy_ipc/AlignmentIndex.py
pyguppyclient/guppy_ipc/AlignmentResults.py
pyguppyclient/guppy_ipc/BarcodeArrangementResults.py
pyguppyclient/guppy_ipc/BarcodeKitDefinition.py
pyguppyclient/guppy_ipc/BarcodeMidDetectResults.py
pyguppyclient/guppy_ipc/BarcodeResults.py
pyguppyclient/guppy_ipc/BaseModData.py
pyguppyclient/guppy_ipc/CalledBlockData.py
pyguppyclient/guppy_ipc/ClientStats.py
pyguppyclient/guppy_ipc/ConfigData.py
pyguppyclient/guppy_ipc/Configuration.py
pyguppyclient/guppy_ipc/Content.py
pyguppyclient/guppy_ipc/FlipflopTraceData.py
pyguppyclient/guppy_ipc/MessageData.py
pyguppyclient/guppy_ipc/ProtocolVersion.py
pyguppyclient/guppy_ipc/ReadBlockData.py
pyguppyclient/guppy_ipc/ReadBlockType.py
pyguppyclient/guppy_ipc/RunlengthTraceData.py
pyguppyclient/guppy_ipc/ScalingData.py
pyguppyclient/guppy_ipc/ScalingOverrideData.py
pyguppyclient/guppy_ipc/ServerStats.py
pyguppyclient/guppy_ipc/SimpleReplyData.py
pyguppyclient/guppy_ipc/SimpleReplyType.py
pyguppyclient/guppy_ipc/SimpleRequestData.py
pyguppyclient/guppy_ipc/SimpleRequestType.py
pyguppyclient/guppy_ipc/TraceData.py
pyguppyclient/guppy_ipc/__init__.py