Metadata-Version: 2.1
Name: pyguppyclient
Version: 0.1.0
Summary: UNKNOWN
Home-page: https://github.com/nanoporetech/pyguppyclient
Author: Oxford Nanopore Technologies, Ltd
Author-email: support@nanoporetech.com
License: UNKNOWN
Platform: UNKNOWN
